prodsys/__init__.py
prodsys/adapters.py
prodsys/analytics/__init__.py
prodsys/analytics/base.py
prodsys/analytics/data_preparation.py
prodsys/analytics/kpi_generator.py
prodsys/analytics/oee.py
prodsys/analytics/production_flow.py
prodsys/analytics/resource_states.py
prodsys/analytics/scrap.py
prodsys/analytics/throughput.py
prodsys/analytics/wip.py
prodsys/conf/__init__.py
prodsys/conf/logging.ini
prodsys/conf/logging_config.py
prodsys/control/__init__.py
prodsys/control/routing_control_env.py
prodsys/control/sequencing_control_env.py
prodsys/express/__init__.py
prodsys/express/core.py
prodsys/express/dependency.py
prodsys/express/node.py
prodsys/express/order.py
prodsys/express/port.py
prodsys/express/primitive.py
prodsys/express/process.py
prodsys/express/product.py
prodsys/express/production_system.py
prodsys/express/resources.py
prodsys/express/sink.py
prodsys/express/source.py
prodsys/express/state.py
prodsys/express/time_model.py
prodsys/factories/__init__.py
prodsys/factories/dependency_factory.py
prodsys/factories/link_transport_process_updater.py
prodsys/factories/node_factory.py
prodsys/factories/port_factory.py
prodsys/factories/primitive_factory.py
prodsys/factories/process_factory.py
prodsys/factories/product_factory.py
prodsys/factories/resource_factory.py
prodsys/factories/router_factory.py
prodsys/factories/sink_factory.py
prodsys/factories/source_factory.py
prodsys/factories/state_factory.py
prodsys/factories/time_model_factory.py
prodsys/models/__init__.py
prodsys/models/core_asset.py
prodsys/models/dependency_data.py
prodsys/models/node_data.py
prodsys/models/order_data.py
prodsys/models/performance_data.py
prodsys/models/performance_indicators.py
prodsys/models/port_data.py
prodsys/models/primitives_data.py
prodsys/models/processes_data.py
prodsys/models/product_data.py
prodsys/models/production_system_data.py
prodsys/models/resource_data.py
prodsys/models/scenario_data.py
prodsys/models/sink_data.py
prodsys/models/source_data.py
prodsys-1.0.5.dist-info/METADATA
prodsys-1.0.5.dist-info/WHEEL
prodsys-1.0.5.dist-info/licenses/LICENSE
prodsys-1.0.5.dist-info/RECORD
