Metadata-Version: 2.4
Name: prodsys
Version: 1.0.5
Summary: A useful module for production system simulation and optimization
Author-email: Sebastian Behrendt <sebastian.behrendt@kit.edu>
License: MIT
License-File: LICENSE
Requires-Python: >=3.10
Requires-Dist: deap>=1.4.3
Requires-Dist: email-validator>=2.3.0
Requires-Dist: gurobipy>=12.0.3
Requires-Dist: importlib-metadata>=8.7.0
Requires-Dist: matplotlib<4.0.0,>=3.7.2
Requires-Dist: numpy<2
Requires-Dist: openpyxl>=3.1.5
Requires-Dist: pandas>=2.3.2
Requires-Dist: pathfinding>=1.0.17
Requires-Dist: plotly>=6.3.0
Requires-Dist: pydantic>=2.11.9
Requires-Dist: pygeoops==0.3.0
Requires-Dist: scikit-image<0.26.0,>=0.25.2
Requires-Dist: scipy>=1.15.3
Requires-Dist: shapely==2.0.2
Requires-Dist: simanneal>=0.5.0
Requires-Dist: simpy>=4.1.1
Requires-Dist: toml>=0.10.2
Requires-Dist: tqdm>=4.67.1
Provides-Extra: dev
Requires-Dist: black>=23.0.0; extra == 'dev'
Requires-Dist: ipykernel>=6.0.0; extra == 'dev'
Requires-Dist: ipywidgets>=8.0.0; extra == 'dev'
Requires-Dist: mkdocs-include-dir-to-nav>=0.0.1; extra == 'dev'
Requires-Dist: mkdocs-material>=9.0.0; extra == 'dev'
Requires-Dist: mkdocstrings-python>=2.0.0; extra == 'dev'
Requires-Dist: mkdocstrings>=0.24.0; extra == 'dev'
Requires-Dist: nbformat>=5.0.0; extra == 'dev'
Requires-Dist: pytest>=7.0.0; extra == 'dev'
Requires-Dist: snakeviz>=2.0.0; extra == 'dev'
Provides-Extra: rl-control
Requires-Dist: gymnasium>=0.29.0; extra == 'rl-control'
Requires-Dist: stable-baselines3>=2.0.0; extra == 'rl-control'
Requires-Dist: tensorboard>=2.11.0; extra == 'rl-control'
